vkmax/__init__.py
vkmax/client.py
vkmax/packet.py
vkmax/functions/__init__.py
vkmax/functions/channels.py
vkmax/functions/groups.py
vkmax/functions/messages.py
vkmax/functions/profile.py
vkmax/functions/users.py
vkmax-1.0.2.dist-info/METADATA
vkmax-1.0.2.dist-info/WHEEL
vkmax-1.0.2.dist-info/top_level.txt
vkmax-1.0.2.dist-info/RECORD
