Metadata-Version: 2.4
Name: vkmax
Version: 1.0.2
Summary: Python client for MAX messenger
Author-email: nsdkinx <nsdkinx@ya.ru>
Project-URL: Homepage, https://github.com/nsdkinx/vkmax
Project-URL: News, https://t.me/max_messenger_python
Keywords: vk,vkapi,max-messenger,vkmax,oneme
Classifier: Programming Language :: Python
Classifier: Programming Language :: Python :: 3
Requires-Python: >=3.9
Requires-Dist: websockets
